bio_curve_fit/__init__.py
bio_curve_fit/base.py
bio_curve_fit/logistic.py
bio_curve_fit/plotting.py
bio_curve_fit-1.1.1.dist-info/METADATA
bio_curve_fit-1.1.1.dist-info/WHEEL
bio_curve_fit-1.1.1.dist-info/licenses/LICENSE
bio_curve_fit-1.1.1.dist-info/RECORD
