Metadata-Version: 2.4
Name: bio-curve-fit
Version: 1.1.1
Summary: Curve fitting algorithms for bio-assays with scikit-learn api
Project-URL: Repository, https://github.com/Ganymede-Bio/bio-curve-fit/
Author-email: Luke Schiefelbein <luke@ganymede.bio>
License: MIT
License-File: LICENSE
Keywords: bio-assay,curve-fitting,data-science,scikit-learn
Requires-Python: >=3.8.12
Requires-Dist: adjusttext>=1.2.0
Requires-Dist: importlib-metadata>=6.0; python_version < '3.8'
Requires-Dist: matplotlib>=3.7.1
Requires-Dist: pandas>=1.5.3
Requires-Dist: scikit-learn>=1.2.2
Provides-Extra: dev
Requires-Dist: coverage>=7.3.2; extra == 'dev'
Requires-Dist: data-science-types>=0.2.23; extra == 'dev'
Requires-Dist: ipykernel>=6.26.0; extra == 'dev'
Requires-Dist: ipython==8.12.2; extra == 'dev'
Requires-Dist: isort>=5.12.0; extra == 'dev'
Requires-Dist: mypy>=1.7.0; extra == 'dev'
Requires-Dist: pre-commit>=3.5.0; extra == 'dev'
Requires-Dist: pytest>=7.4.3; extra == 'dev'
Requires-Dist: ruff>=0.1.5; extra == 'dev'
